biotransistor/__init__.py
biotransistor/_version.py
biotransistor/cellborder_hack.20200911.py
biotransistor/cellborder_hack.20200912.py
biotransistor/hgenes.py
biotransistor/hgenes_cmif.py
biotransistor/imagine.20201013superfast.py
biotransistor/imagine.py
biotransistor/pytex.py
biotransistor-0.0.3.dist-info/LICENSE
biotransistor-0.0.3.dist-info/METADATA
biotransistor-0.0.3.dist-info/WHEEL
biotransistor-0.0.3.dist-info/top_level.txt
biotransistor-0.0.3.dist-info/RECORD
